yargy/__init__.py
yargy/api.py
yargy/check.py
yargy/dot.py
yargy/morph.py
yargy/parser.py
yargy/pipelines.py
yargy/record.py
yargy/span.py
yargy/tagger.py
yargy/token.py
yargy/tokenizer.py
yargy/visitor.py
yargy/interpretation/__init__.py
yargy/interpretation/attribute.py
yargy/interpretation/fact.py
yargy/interpretation/interpretator.py
yargy/interpretation/normalizer.py
yargy/predicates/__init__.py
yargy/predicates/bank.py
yargy/predicates/constructors.py
yargy/relations/__init__.py
yargy/relations/bank.py
yargy/relations/constructors.py
yargy/relations/graph.py
yargy/rule/__init__.py
yargy/rule/bnf.py
yargy/rule/constructors.py
yargy/rule/transformators.py
yargy/tree/__init__.py
yargy/tree/constructors.py
yargy/tree/transformators.py
yargy-0.16.0.dist-info/LICENSE
yargy-0.16.0.dist-info/METADATA
yargy-0.16.0.dist-info/WHEEL
yargy-0.16.0.dist-info/top_level.txt
yargy-0.16.0.dist-info/RECORD
