Metadata-Version: 2.1
Name: yargy
Version: 0.16.0
Summary: Rule-based facts extraction for Russian language
Home-page: https://github.com/natasha/yargy
Author: Yargy contributors
Author-email: d.a.veselov@yandex.ru, alex@alexkuk.ru
License: MIT
Keywords: natural language processing,russian morphology,glr,parser
Classifier: Intended Audience :: Developers
Classifier: License :: OSI Approved :: MIT License
License-File: LICENSE
